image_gen_mcp/__init__.py
image_gen_mcp/exceptions.py
image_gen_mcp/main.py
image_gen_mcp/schema.py
image_gen_mcp/settings.py
image_gen_mcp/engines/__init__.py
image_gen_mcp/engines/base_engine.py
image_gen_mcp/engines/factory.py
image_gen_mcp/engines/ar/gemini.py
image_gen_mcp/engines/ar/openai.py
image_gen_mcp/engines/ar/openrouter.py
image_gen_mcp/engines/diffusion/dalle_diffusion.py
image_gen_mcp/engines/diffusion/vertex_imagen.py
image_gen_mcp/shard/constants.py
image_gen_mcp/shard/enums.py
image_gen_mcp/shard/instructions.py
image_gen_mcp/utils/error_helpers.py
image_gen_mcp/utils/image_utils.py
image_gen_mcp/utils/prompt.py
image_gen_mcp-1.4.0.dist-info/METADATA
image_gen_mcp-1.4.0.dist-info/WHEEL
image_gen_mcp-1.4.0.dist-info/entry_points.txt
image_gen_mcp-1.4.0.dist-info/licenses/LICENSE
image_gen_mcp-1.4.0.dist-info/RECORD
