Metadata-Version: 2.4
Name: image-gen-mcp
Version: 1.4.0
Summary: MCP image generation server with modular engines and routing
Project-URL: Homepage, https://github.com/simonChoi034/image-gen-mcp
Project-URL: Repository, https://github.com/simonChoi034/image-gen-mcp
Project-URL: Issues, https://github.com/simonChoi034/image-gen-mcp/issues
Project-URL: Changelog, https://github.com/simonChoi034/image-gen-mcp/releases
Author-email: Simon Choi <simon.choi034@gmail.com>
Maintainer-email: Simon Choi <simon.choi034@gmail.com>
License: MIT
License-File: LICENSE
Keywords: ai,dall-e,gemini,image-generation,imagen,mcp,model-context-protocol,openai,vertex-ai
Classifier: Development Status :: 4 - Beta
Classifier: Intended Audience :: Developers
Classifier: License :: OSI Approved :: MIT License
Classifier: Programming Language :: Python :: 3
Classifier: Programming Language :: Python :: 3.12
Classifier: Programming Language :: Python :: 3.13
Classifier: Topic :: Multimedia :: Graphics
Classifier: Topic :: Scientific/Engineering :: Artificial Intelligence
Classifier: Topic :: Software Development :: Libraries :: Python Modules
Requires-Python: >=3.12
Requires-Dist: fastmcp>=2.12.2
Requires-Dist: google-genai>=0.3.0
Requires-Dist: httpx>=0.27.0
Requires-Dist: jinja2>=3.1.6
Requires-Dist: loguru>=0.7.3
Requires-Dist: mcp>=1.0.0
Requires-Dist: openai>=1.40.0
Requires-Dist: pillow>=10.0.0
Requires-Dist: pydantic-settings>=2.3.0
Requires-Dist: pydantic>=2.8.0
Requires-Dist: typing-extensions>=4.12.0
Provides-Extra: dev
Requires-Dist: black>=24.4.2; extra == 'dev'
Requires-Dist: pyright>=1.1.379; extra == 'dev'
Requires-Dist: pytest>=8.3.0; extra == 'dev'
Requires-Dist: ruff>=0.5.0; extra == 'dev'
